[
  {
    "id": "175b8608bfe7",
    "title": "BRAC University - Lecturer - Jobs",
    "institution": "BDJobs",
    "source": "BDJobs",
    "url": "https://jobs.bdjobs.com/jobdetails/?id=1491602&fcatId=4&ln=1",
    "deadline": "",
    "found_at": "2026-06-24T10:51:26.146593+00:00",
    "notified": false
  },
  {
    "id": "5ce8c31756da",
    "title": "Computer Science and Engineering- State University of Bangladesh",
    "institution": "Web",
    "source": "Web",
    "url": "https://sub.ac.bd/department/computer-science-and-engineering",
    "deadline": "",
    "found_at": "2026-06-24T10:51:33.994645+00:00",
    "notified": false
  }
]